{
  "schemaVersion": "echo.official_modpack.release_audit.v1",
  "status": "rebuilt-from-current-module-catalog",
  "pack": "ashfall-standalone-edition",
  "name": "Ashfall Standalone Edition",
  "version": "0.1.2",
  "channel": "beta",
  "moduleRelease": "modules-beta-full-20260620",
  "moduleSourceRevision": "ECHO-Modules afd206900713 local Content Graph + AdapterCore recovery artifacts, 2026-06-20",
  "releaseTag": "v0.1.2-ashfall-standalone-edition-beta.3",
  "sourceRepo": "knoxhack/ECHO-Ashfall-Standalone-Edition",
  "moduleCount": 46,
  "artifact": {
    "name": "ashfall-standalone-edition-0.1.2.zip",
    "sha256": "bd9a7a7bf229166f5ed1922a4cd08f55b0dfe121adfabd1613c770406edc6473",
    "size": 269678964
  },
  "manifest": {
    "name": "ashfall-standalone-edition-beta-0.1.2.pack.json",
    "sha256": "334d67cac30b87b1ae92f082f40259eaa90bbba80cb6f7050379ce605881df1e",
    "size": 59619
  },
  "generatedAt": "2026-06-20T00:00:00.000Z"
}
